mvg/__init__.py
mvg/mvgapi.py
mvg-1.5.0.dist-info/METADATA
mvg-1.5.0.dist-info/WHEEL
mvg-1.5.0.dist-info/licenses/LICENSE
mvg-1.5.0.dist-info/RECORD
