Metadata-Version: 2.4
Name: mvg
Version: 1.5.0
Summary: An unofficial interface to timetable information of the Münchner Verkehrsgesellschaft (MVG).
Project-URL: Documentation, https://mondbaron.github.io/mvg
Project-URL: Source, https://github.com/mondbaron/mvg
Project-URL: Bug Tracker, https://github.com/mondbaron/mvg/issues
Author-email: Martin Dziura <m.dziura@tum.de>
License: MIT
License-File: LICENSE
Classifier: License :: OSI Approved :: MIT License
Classifier: Operating System :: OS Independent
Classifier: Programming Language :: Python :: 3
Requires-Python: >=3.8
Requires-Dist: aiohttp~=3.8
Requires-Dist: furl~=2.1
Provides-Extra: dev
Requires-Dist: mypy; extra == 'dev'
Requires-Dist: pytest; extra == 'dev'
Requires-Dist: pytest-asyncio; extra == 'dev'
Requires-Dist: ruff; extra == 'dev'
Requires-Dist: sphinx; extra == 'dev'
Requires-Dist: sphinx-mdinclude; extra == 'dev'
Requires-Dist: sphinx-pyproject; extra == 'dev'
Requires-Dist: sphinx-rtd-theme; extra == 'dev'
Requires-Dist: tox; extra == 'dev'
Requires-Dist: tox-uv; extra == 'dev'
